README.md
setup.py
yhs_menu/__init__.py
yhs_menu.egg-info/PKG-INFO
yhs_menu.egg-info/SOURCES.txt
yhs_menu.egg-info/dependency_links.txt
yhs_menu.egg-info/requires.txt
yhs_menu.egg-info/top_level.txt