Metadata-Version: 2.1
Name: yhs-menu
Version: 1.0.1
Summary: A light weight command line menu that supports Windows, MacOS, and Linux
Home-page: UNKNOWN
Author: yhs
Author-email: 
License: UNKNOWN
Keywords: python,menu,yhs_menu,windows,mac,linux
Platform: UNKNOWN
Classifier: Development Status :: 1 - Planning
Classifier: Intended Audience :: Developers
Classifier: Programming Language :: Python :: 3
Classifier: Operating System :: Unix
Classifier: Operating System :: MacOS :: MacOS X
Classifier: Operating System :: Microsoft :: Windows
